environment_manager/__init__.py
environment_manager/api.py
environment_manager/utils.py
pyclingmerv-0.2.15.dist-info/DESCRIPTION.rst
pyclingmerv-0.2.15.dist-info/METADATA
pyclingmerv-0.2.15.dist-info/RECORD
pyclingmerv-0.2.15.dist-info/WHEEL
pyclingmerv-0.2.15.dist-info/metadata.json
pyclingmerv-0.2.15.dist-info/top_level.txt
pyclingmerv-0.2.15.dist-info/zip-safe
